tb/cocotb/drom_nco/drom_nco.v
// {"dataWidth":16,"addrWidth":0,"betaWidth":14,"nCordics":8,"corrector":0,"scale":0.999999}
module drom_nco (
    // per node (target / initiator)
    input              clk,
    input              reset_n,
    input       [31:0] t_angle_dat,
    input              t_angle_req,
    output             t_angle_ack,
    output      [31:0] i_nco_dat,
    output             i_nco_req,
    input              i_nco_ack
);
// per edge
wire      [31:0] dat0, dat0_nxt;
wire      [67:0] dat1, dat1_nxt;
wire      [67:0] dat2, dat2_nxt;
wire      [67:0] dat3, dat3_nxt;
wire      [67:0] dat4, dat4_nxt;
wire      [67:0] dat5, dat5_nxt;
wire      [67:0] dat6, dat6_nxt;
wire      [67:0] dat7, dat7_nxt;
wire      [67:0] dat8, dat8_nxt;
wire      [67:0] dat9, dat9_nxt;
wire      [31:0] dat10;
// per node
// node:0 is target port
assign dat0_nxt = t_angle_dat;

// node:1 macro nco_lut

// Look-Up stage
/*
{JSON.stringify(lut, null, 4)}
*/

reg [31:0] ncolut;

always @*
casez (node1_addr)
0 : ncolut = {16'd25072, 16'd60529};
endcase

wire [31:0] node1_angle;
wire [2:0] node1_phase;
wire [-1:0] node1_addr;
wire [17:0] node1_reSwap;
wire [17:0] node1_imSwap;


assign node1_angle = dat0;
assign node1_phase = node1_angle[31:29]; //3 bit phase
assign node1_addr = node1_phase[0]?~node1_angle[29:28]:node1_angle[29:28];
//re = 15:0  im = 31:16
assign node1_reSwap[17:16]=2'b0;
assign node1_imSwap[17:16]=2'b0;
assign node1_reSwap[15:0] = node1_phase[0]^node1_phase[1] ? ncolut[31:16]:ncolut[15:0];
assign node1_imSwap[15:0] = node1_phase[0]^node1_phase[1] ? ncolut[15:0]:ncolut[31:16];

assign dat1_nxt[17:0] = node1_phase[2]^node1_phase[1]?~node1_reSwap:node1_reSwap;
assign dat1_nxt[35:18] = node1_phase[2]?~node1_imSwap:node1_imSwap;
assign dat1_nxt[64:36] = node1_angle[28:0];

// node:2 macro nco_cordic

// CORDIC stage 0
/*
{
    "sigma": 5106,
    "shift": 2
}
*/

wire [28:0] beta0;
wire [28:0] beta_calc0;
wire [17:0] re0,im0,re_shift0,im_shift0;


assign  beta0 = dat1[28:0];

assign re0=dat1[17:0];
assign im0=dat1[35:18];

//assign re_shift0={{2{re0[17]}},re0 >> 2};
//assign im_shift0={{2{im0[17]}},im0 >> 2};

assign re_shift0=$signed(re0) >> 2;
assign im_shift0=$signed(im0) >> 2;

assign beta_calc0 = beta0[28]?beta0+5106:beta0-5106;
assign dat2_nxt[17:0] = beta0[28]?re0-im_shift0 : re0+im_shift0;
assign dat2_nxt[35:18] = beta0[28]?im0+re_shift0 : im0-re_shift0;
assign dat2_nxt[64:36] = beta_calc0;


// node:3 macro nco_cordic

// CORDIC stage 1
/*
{
    "sigma": 2592,
    "shift": 3
}
*/

wire [28:0] beta1;
wire [28:0] beta_calc1;
wire [17:0] re1,im1,re_shift1,im_shift1;


assign  beta1 = dat2[28:0];

assign re1=dat2[17:0];
assign im1=dat2[35:18];

//assign re_shift1={{3{re1[17]}},re1 >> 3};
//assign im_shift1={{3{im1[17]}},im1 >> 3};

assign re_shift1=$signed(re1) >> 3;
assign im_shift1=$signed(im1) >> 3;

assign beta_calc1 = beta1[28]?beta1+2592:beta1-2592;
assign dat3_nxt[17:0] = beta1[28]?re1-im_shift1 : re1+im_shift1;
assign dat3_nxt[35:18] = beta1[28]?im1+re_shift1 : im1-re_shift1;
assign dat3_nxt[64:36] = beta_calc1;


// node:4 macro nco_cordic

// CORDIC stage 2
/*
{
    "sigma": 1301,
    "shift": 4
}
*/

wire [28:0] beta2;
wire [28:0] beta_calc2;
wire [17:0] re2,im2,re_shift2,im_shift2;


assign  beta2 = dat3[28:0];

assign re2=dat3[17:0];
assign im2=dat3[35:18];

//assign re_shift2={{4{re2[17]}},re2 >> 4};
//assign im_shift2={{4{im2[17]}},im2 >> 4};

assign re_shift2=$signed(re2) >> 4;
assign im_shift2=$signed(im2) >> 4;

assign beta_calc2 = beta2[28]?beta2+1301:beta2-1301;
assign dat4_nxt[17:0] = beta2[28]?re2-im_shift2 : re2+im_shift2;
assign dat4_nxt[35:18] = beta2[28]?im2+re_shift2 : im2-re_shift2;
assign dat4_nxt[64:36] = beta_calc2;


// node:5 macro nco_cordic

// CORDIC stage 3
/*
{
    "sigma": 651,
    "shift": 5
}
*/

wire [28:0] beta3;
wire [28:0] beta_calc3;
wire [17:0] re3,im3,re_shift3,im_shift3;


assign  beta3 = dat4[28:0];

assign re3=dat4[17:0];
assign im3=dat4[35:18];

//assign re_shift3={{5{re3[17]}},re3 >> 5};
//assign im_shift3={{5{im3[17]}},im3 >> 5};

assign re_shift3=$signed(re3) >> 5;
assign im_shift3=$signed(im3) >> 5;

assign beta_calc3 = beta3[28]?beta3+651:beta3-651;
assign dat5_nxt[17:0] = beta3[28]?re3-im_shift3 : re3+im_shift3;
assign dat5_nxt[35:18] = beta3[28]?im3+re_shift3 : im3-re_shift3;
assign dat5_nxt[64:36] = beta_calc3;


// node:6 macro nco_cordic

// CORDIC stage 4
/*
{
    "sigma": 326,
    "shift": 6
}
*/

wire [28:0] beta4;
wire [28:0] beta_calc4;
wire [17:0] re4,im4,re_shift4,im_shift4;


assign  beta4 = dat5[28:0];

assign re4=dat5[17:0];
assign im4=dat5[35:18];

//assign re_shift4={{6{re4[17]}},re4 >> 6};
//assign im_shift4={{6{im4[17]}},im4 >> 6};

assign re_shift4=$signed(re4) >> 6;
assign im_shift4=$signed(im4) >> 6;

assign beta_calc4 = beta4[28]?beta4+326:beta4-326;
assign dat6_nxt[17:0] = beta4[28]?re4-im_shift4 : re4+im_shift4;
assign dat6_nxt[35:18] = beta4[28]?im4+re_shift4 : im4-re_shift4;
assign dat6_nxt[64:36] = beta_calc4;


// node:7 macro nco_cordic

// CORDIC stage 5
/*
{
    "sigma": 163,
    "shift": 7
}
*/

wire [28:0] beta5;
wire [28:0] beta_calc5;
wire [17:0] re5,im5,re_shift5,im_shift5;


assign  beta5 = dat6[28:0];

assign re5=dat6[17:0];
assign im5=dat6[35:18];

//assign re_shift5={{7{re5[17]}},re5 >> 7};
//assign im_shift5={{7{im5[17]}},im5 >> 7};

assign re_shift5=$signed(re5) >> 7;
assign im_shift5=$signed(im5) >> 7;

assign beta_calc5 = beta5[28]?beta5+163:beta5-163;
assign dat7_nxt[17:0] = beta5[28]?re5-im_shift5 : re5+im_shift5;
assign dat7_nxt[35:18] = beta5[28]?im5+re_shift5 : im5-re_shift5;
assign dat7_nxt[64:36] = beta_calc5;


// node:8 macro nco_cordic

// CORDIC stage 6
/*
{
    "sigma": 81,
    "shift": 8
}
*/

wire [28:0] beta6;
wire [28:0] beta_calc6;
wire [17:0] re6,im6,re_shift6,im_shift6;


assign  beta6 = dat7[28:0];

assign re6=dat7[17:0];
assign im6=dat7[35:18];

//assign re_shift6={{8{re6[17]}},re6 >> 8};
//assign im_shift6={{8{im6[17]}},im6 >> 8};

assign re_shift6=$signed(re6) >> 8;
assign im_shift6=$signed(im6) >> 8;

assign beta_calc6 = beta6[28]?beta6+81:beta6-81;
assign dat8_nxt[17:0] = beta6[28]?re6-im_shift6 : re6+im_shift6;
assign dat8_nxt[35:18] = beta6[28]?im6+re_shift6 : im6-re_shift6;
assign dat8_nxt[64:36] = beta_calc6;


// node:9 macro nco_cordic

// CORDIC stage 7
/*
{
    "sigma": 41,
    "shift": 9
}
*/

wire [28:0] beta7;
wire [28:0] beta_calc7;
wire [17:0] re7,im7,re_shift7,im_shift7;


assign  beta7 = dat8[28:0];

assign re7=dat8[17:0];
assign im7=dat8[35:18];

//assign re_shift7={{9{re7[17]}},re7 >> 9};
//assign im_shift7={{9{im7[17]}},im7 >> 9};

assign re_shift7=$signed(re7) >> 9;
assign im_shift7=$signed(im7) >> 9;

assign beta_calc7 = beta7[28]?beta7+41:beta7-41;
assign dat9_nxt[17:0] = beta7[28]?re7-im_shift7 : re7+im_shift7;
assign dat9_nxt[35:18] = beta7[28]?im7+re_shift7 : im7-re_shift7;
assign dat9_nxt[64:36] = beta_calc7;


// node:10 macro saturation

wire [17:0] recalc10,imcalc10;
wire [15:0] redata10,imdata10;

assign recalc10=dat9[17:0];
assign imcalc10=dat9[35:18];

assign dat10[15:0]=^recalc10[17:16]?{recalc10[17],{15{~recalc10[17]}}}:{recalc10[17],recalc10[15:1]};

assign dat10[31:16]=^imcalc10[17:16]?{imcalc10[17],{15{~imcalc10[17]}}}:{imcalc10[17],imcalc10[15:1]};

assign redata10 = dat10[15:0];
assign imdata10 = dat10[31:16];


// node:11 is initiator port
assign i_nco_dat = dat10;

// per edge

// edge:0 EB1
wire en0;
reg [31:0] dat0_r;
always @(posedge clk) if (en0) dat0_r <= dat0_nxt;
assign dat0 = dat0_r;


// edge:1 EB1
wire en1;
reg [67:0] dat1_r;
always @(posedge clk) if (en1) dat1_r <= dat1_nxt;
assign dat1 = dat1_r;


// edge:2 EB1
wire en2;
reg [67:0] dat2_r;
always @(posedge clk) if (en2) dat2_r <= dat2_nxt;
assign dat2 = dat2_r;


// edge:3 EB1
wire en3;
reg [67:0] dat3_r;
always @(posedge clk) if (en3) dat3_r <= dat3_nxt;
assign dat3 = dat3_r;


// edge:4 EB1
wire en4;
reg [67:0] dat4_r;
always @(posedge clk) if (en4) dat4_r <= dat4_nxt;
assign dat4 = dat4_r;


// edge:5 EB1
wire en5;
reg [67:0] dat5_r;
always @(posedge clk) if (en5) dat5_r <= dat5_nxt;
assign dat5 = dat5_r;


// edge:6 EB1
wire en6;
reg [67:0] dat6_r;
always @(posedge clk) if (en6) dat6_r <= dat6_nxt;
assign dat6 = dat6_r;


// edge:7 EB1
wire en7;
reg [67:0] dat7_r;
always @(posedge clk) if (en7) dat7_r <= dat7_nxt;
assign dat7 = dat7_r;


// edge:8 EB1
wire en8;
reg [67:0] dat8_r;
always @(posedge clk) if (en8) dat8_r <= dat8_nxt;
assign dat8 = dat8_r;


// edge:9 EB1
wire en9;
reg [67:0] dat9_r;
always @(posedge clk) if (en9) dat9_r <= dat9_nxt;
assign dat9 = dat9_r;


// edge:10 EB0

nco_ctrl uctrl (
    .clk(clk),
    .reset_n(reset_n),
    .t_angle_req(t_angle_req),
    .t_angle_ack(t_angle_ack),
    .i_nco_req(i_nco_req),
    .i_nco_ack(i_nco_ack),
    .en0(en0),
    .en1(en1),
    .en2(en2),
    .en3(en3),
    .en4(en4),
    .en5(en5),
    .en6(en6),
    .en7(en7),
    .en8(en8),
    .en9(en9)
);
endmodule // nco

module nco_ctrl (
    // per node (target / initiator)
    input              clk,
    input              reset_n,
    input              t_angle_req,
    output             t_angle_ack,
    output             i_nco_req,
    input              i_nco_ack,
    output             en0,
    output             en1,
    output             en2,
    output             en3,
    output             en4,
    output             en5,
    output             en6,
    output             en7,
    output             en8,
    output             en9
);
// per edge
wire             req0, ack0, ack0_0, req0_0;
wire             req1, ack1, ack1_0, req1_0;
wire             req2, ack2, ack2_0, req2_0;
wire             req3, ack3, ack3_0, req3_0;
wire             req4, ack4, ack4_0, req4_0;
wire             req5, ack5, ack5_0, req5_0;
wire             req6, ack6, ack6_0, req6_0;
wire             req7, ack7, ack7_0, req7_0;
wire             req8, ack8, ack8_0, req8_0;
wire             req9, ack9, ack9_0, req9_0;
wire             req10, ack10, ack10_0, req10_0;
// node:t_angle target
assign req0 = t_angle_req;
assign t_angle_ack = ack0;

// edge:0 EB1
wire ack0m;
reg req0m;
assign en0 = req0 & ack0;
assign ack0 = ~req0m | ack0m;
always @(posedge clk or negedge reset_n) if (~reset_n) req0m <= 1'b0; else req0m <= ~ack0 | req0;


// edge:0 fork


assign req0_0 = req0m;

assign ack0m = ack0_0;



// edge:1 EB1
wire ack1m;
reg req1m;
assign en1 = req1 & ack1;
assign ack1 = ~req1m | ack1m;
always @(posedge clk or negedge reset_n) if (~reset_n) req1m <= 1'b0; else req1m <= ~ack1 | req1;


// edge:1 fork


assign req1_0 = req1m;

assign ack1m = ack1_0;



// edge:2 EB1
wire ack2m;
reg req2m;
assign en2 = req2 & ack2;
assign ack2 = ~req2m | ack2m;
always @(posedge clk or negedge reset_n) if (~reset_n) req2m <= 1'b0; else req2m <= ~ack2 | req2;


// edge:2 fork


assign req2_0 = req2m;

assign ack2m = ack2_0;



// edge:3 EB1
wire ack3m;
reg req3m;
assign en3 = req3 & ack3;
assign ack3 = ~req3m | ack3m;
always @(posedge clk or negedge reset_n) if (~reset_n) req3m <= 1'b0; else req3m <= ~ack3 | req3;


// edge:3 fork


assign req3_0 = req3m;

assign ack3m = ack3_0;



// edge:4 EB1
wire ack4m;
reg req4m;
assign en4 = req4 & ack4;
assign ack4 = ~req4m | ack4m;
always @(posedge clk or negedge reset_n) if (~reset_n) req4m <= 1'b0; else req4m <= ~ack4 | req4;


// edge:4 fork


assign req4_0 = req4m;

assign ack4m = ack4_0;



// edge:5 EB1
wire ack5m;
reg req5m;
assign en5 = req5 & ack5;
assign ack5 = ~req5m | ack5m;
always @(posedge clk or negedge reset_n) if (~reset_n) req5m <= 1'b0; else req5m <= ~ack5 | req5;


// edge:5 fork


assign req5_0 = req5m;

assign ack5m = ack5_0;



// edge:6 EB1
wire ack6m;
reg req6m;
assign en6 = req6 & ack6;
assign ack6 = ~req6m | ack6m;
always @(posedge clk or negedge reset_n) if (~reset_n) req6m <= 1'b0; else req6m <= ~ack6 | req6;


// edge:6 fork


assign req6_0 = req6m;

assign ack6m = ack6_0;



// edge:7 EB1
wire ack7m;
reg req7m;
assign en7 = req7 & ack7;
assign ack7 = ~req7m | ack7m;
always @(posedge clk or negedge reset_n) if (~reset_n) req7m <= 1'b0; else req7m <= ~ack7 | req7;


// edge:7 fork


assign req7_0 = req7m;

assign ack7m = ack7_0;



// edge:8 EB1
wire ack8m;
reg req8m;
assign en8 = req8 & ack8;
assign ack8 = ~req8m | ack8m;
always @(posedge clk or negedge reset_n) if (~reset_n) req8m <= 1'b0; else req8m <= ~ack8 | req8;


// edge:8 fork


assign req8_0 = req8m;

assign ack8m = ack8_0;



// edge:9 EB1
wire ack9m;
reg req9m;
assign en9 = req9 & ack9;
assign ack9 = ~req9m | ack9m;
always @(posedge clk or negedge reset_n) if (~reset_n) req9m <= 1'b0; else req9m <= ~ack9 | req9;


// edge:9 fork


assign req9_0 = req9m;

assign ack9m = ack9_0;



// edge:10 EB0
wire ack10m, req10m;
assign req10m = req10;
assign ack10 = ack10m;


// edge:10 fork


assign req10_0 = req10m;

assign ack10m = ack10_0;


// node:1 join nco_lut
assign req1 = req0_0;
assign ack0_0 = ack1;
// node:2 join nco_cordic
assign req2 = req1_0;
assign ack1_0 = ack2;
// node:3 join nco_cordic
assign req3 = req2_0;
assign ack2_0 = ack3;
// node:4 join nco_cordic
assign req4 = req3_0;
assign ack3_0 = ack4;
// node:5 join nco_cordic
assign req5 = req4_0;
assign ack4_0 = ack5;
// node:6 join nco_cordic
assign req6 = req5_0;
assign ack5_0 = ack6;
// node:7 join nco_cordic
assign req7 = req6_0;
assign ack6_0 = ack7;
// node:8 join nco_cordic
assign req8 = req7_0;
assign ack7_0 = ack8;
// node:9 join nco_cordic
assign req9 = req8_0;
assign ack8_0 = ack9;
// node:10 join saturation
assign req10 = req9_0;
assign ack9_0 = ack10;
// node:11 initiator
assign i_nco_req = req10_0;
assign ack10_0 = i_nco_ack;

`ifdef COCOTB_SIM
initial begin
  $dumpfile ("drom_nco.vcd");
  $dumpvars (0, drom_nco);
  #1;
end
`endif

endmodule // nco_ctrl

tb/cocotb/drom_nco/drom_nco.vcd
$date
	Sun Sep 27 16:11:37 2020
$end
$version
	Icarus Verilog
$end
$timescale
	1ps
$end
$scope module drom_nco $end
$var wire 1 ! clk $end
$var wire 32 " dat0_nxt [31:0] $end
$var wire 1 # i_nco_ack $end
$var wire 32 $ i_nco_dat [31:0] $end
$var wire 32 % node1_angle [31:0] $end
$var wire 1 & reset_n $end
$var wire 32 ' t_angle_dat [31:0] $end
$var wire 1 ( t_angle_req $end
$var wire 1 ) t_angle_ack $end
$var wire 16 * redata10 [15:0] $end
$var wire 18 + recalc10 [17:0] $end
$var wire 18 , re_shift7 [17:0] $end
$var wire 18 - re_shift6 [17:0] $end
$var wire 18 . re_shift5 [17:0] $end
$var wire 18 / re_shift4 [17:0] $end
$var wire 18 0 re_shift3 [17:0] $end
$var wire 18 1 re_shift2 [17:0] $end
$var wire 18 2 re_shift1 [17:0] $end
$var wire 18 3 re_shift0 [17:0] $end
$var wire 18 4 re7 [17:0] $end
$var wire 18 5 re6 [17:0] $end
$var wire 18 6 re5 [17:0] $end
$var wire 18 7 re4 [17:0] $end
$var wire 18 8 re3 [17:0] $end
$var wire 18 9 re2 [17:0] $end
$var wire 18 : re1 [17:0] $end
$var wire 18 ; re0 [17:0] $end
$var wire 18 < node1_reSwap [17:0] $end
$var wire 3 = node1_phase [2:0] $end
$var wire 18 > node1_imSwap [17:0] $end
$var wire 2 ? node1_addr [-1:0] $end
$var wire 16 @ imdata10 [15:0] $end
$var wire 18 A imcalc10 [17:0] $end
$var wire 18 B im_shift7 [17:0] $end
$var wire 18 C im_shift6 [17:0] $end
$var wire 18 D im_shift5 [17:0] $end
$var wire 18 E im_shift4 [17:0] $end
$var wire 18 F im_shift3 [17:0] $end
$var wire 18 G im_shift2 [17:0] $end
$var wire 18 H im_shift1 [17:0] $end
$var wire 18 I im_shift0 [17:0] $end
$var wire 18 J im7 [17:0] $end
$var wire 18 K im6 [17:0] $end
$var wire 18 L im5 [17:0] $end
$var wire 18 M im4 [17:0] $end
$var wire 18 N im3 [17:0] $end
$var wire 18 O im2 [17:0] $end
$var wire 18 P im1 [17:0] $end
$var wire 18 Q im0 [17:0] $end
$var wire 1 R i_nco_req $end
$var wire 1 S en9 $end
$var wire 1 T en8 $end
$var wire 1 U en7 $end
$var wire 1 V en6 $end
$var wire 1 W en5 $end
$var wire 1 X en4 $end
$var wire 1 Y en3 $end
$var wire 1 Z en2 $end
$var wire 1 [ en1 $end
$var wire 1 \ en0 $end
$var wire 68 ] dat9_nxt [67:0] $end
$var wire 68 ^ dat9 [67:0] $end
$var wire 68 _ dat8_nxt [67:0] $end
$var wire 68 ` dat8 [67:0] $end
$var wire 68 a dat7_nxt [67:0] $end
$var wire 68 b dat7 [67:0] $end
$var wire 68 c dat6_nxt [67:0] $end
$var wire 68 d dat6 [67:0] $end
$var wire 68 e dat5_nxt [67:0] $end
$var wire 68 f dat5 [67:0] $end
$var wire 68 g dat4_nxt [67:0] $end
$var wire 68 h dat4 [67:0] $end
$var wire 68 i dat3_nxt [67:0] $end
$var wire 68 j dat3 [67:0] $end
$var wire 68 k dat2_nxt [67:0] $end
$var wire 68 l dat2 [67:0] $end
$var wire 68 m dat1_nxt [67:0] $end
$var wire 32 n dat10 [31:0] $end
$var wire 68 o dat1 [67:0] $end
$var wire 32 p dat0 [31:0] $end
$var wire 29 q beta_calc7 [28:0] $end
$var wire 29 r beta_calc6 [28:0] $end
$var wire 29 s beta_calc5 [28:0] $end
$var wire 29 t beta_calc4 [28:0] $end
$var wire 29 u beta_calc3 [28:0] $end
$var wire 29 v beta_calc2 [28:0] $end
$var wire 29 w beta_calc1 [28:0] $end
$var wire 29 x beta_calc0 [28:0] $end
$var wire 29 y beta7 [28:0] $end
$var wire 29 z beta6 [28:0] $end
$var wire 29 { beta5 [28:0] $end
$var wire 29 | beta4 [28:0] $end
$var wire 29 } beta3 [28:0] $end
$var wire 29 ~ beta2 [28:0] $end
$var wire 29 !" beta1 [28:0] $end
$var wire 29 "" beta0 [28:0] $end
$var reg 32 #" dat0_r [31:0] $end
$var reg 68 $" dat1_r [67:0] $end
$var reg 68 %" dat2_r [67:0] $end
$var reg 68 &" dat3_r [67:0] $end
$var reg 68 '" dat4_r [67:0] $end
$var reg 68 (" dat5_r [67:0] $end
$var reg 68 )" dat6_r [67:0] $end
$var reg 68 *" dat7_r [67:0] $end
$var reg 68 +" dat8_r [67:0] $end
$var reg 68 ," dat9_r [67:0] $end
$var reg 32 -" ncolut [31:0] $end
$scope module uctrl $end
$var wire 1 ." ack0 $end
$var wire 1 /" ack0_0 $end
$var wire 1 0" ack0m $end
$var wire 1 1" ack1 $end
$var wire 1 2" ack10 $end
$var wire 1 3" ack10_0 $end
$var wire 1 4" ack10m $end
$var wire 1 5" ack1_0 $end
$var wire 1 6" ack1m $end
$var wire 1 7" ack2 $end
$var wire 1 8" ack2_0 $end
$var wire 1 9" ack2m $end
$var wire 1 :" ack3 $end
$var wire 1 ;" ack3_0 $end
$var wire 1 <" ack3m $end
$var wire 1 =" ack4 $end
$var wire 1 >" ack4_0 $end
$var wire 1 ?" ack4m $end
$var wire 1 @" ack5 $end
$var wire 1 A" ack5_0 $end
$var wire 1 B" ack5m $end
$var wire 1 C" ack6 $end
$var wire 1 D" ack6_0 $end
$var wire 1 E" ack6m $end
$var wire 1 F" ack7 $end
$var wire 1 G" ack7_0 $end
$var wire 1 H" ack7m $end
$var wire 1 I" ack8 $end
$var wire 1 J" ack8_0 $end
$var wire 1 K" ack8m $end
$var wire 1 L" ack9 $end
$var wire 1 M" ack9_0 $end
$var wire 1 N" ack9m $end
$var wire 1 ! clk $end
$var wire 1 \ en0 $end
$var wire 1 [ en1 $end
$var wire 1 Z en2 $end
$var wire 1 Y en3 $end
$var wire 1 X en4 $end
$var wire 1 W en5 $end
$var wire 1 V en6 $end
$var wire 1 U en7 $end
$var wire 1 T en8 $end
$var wire 1 S en9 $end
$var wire 1 # i_nco_ack $end
$var wire 1 R i_nco_req $end
$var wire 1 O" req0 $end
$var wire 1 P" req0_0 $end
$var wire 1 Q" req1 $end
$var wire 1 R" req10 $end
$var wire 1 S" req10_0 $end
$var wire 1 T" req10m $end
$var wire 1 U" req1_0 $end
$var wire 1 V" req2 $end
$var wire 1 W" req2_0 $end
$var wire 1 X" req3 $end
$var wire 1 Y" req3_0 $end
$var wire 1 Z" req4 $end
$var wire 1 [" req4_0 $end
$var wire 1 \" req5 $end
$var wire 1 ]" req5_0 $end
$var wire 1 ^" req6 $end
$var wire 1 _" req6_0 $end
$var wire 1 `" req7 $end
$var wire 1 a" req7_0 $end
$var wire 1 b" req8 $end
$var wire 1 c" req8_0 $end
$var wire 1 d" req9 $end
$var wire 1 e" req9_0 $end
$var wire 1 & reset_n $end
$var wire 1 ) t_angle_ack $end
$var wire 1 ( t_angle_req $end
$var reg 1 f" req0m $end
$var reg 1 g" req1m $end
$var reg 1 h" req2m $end
$var reg 1 i" req3m $end
$var reg 1 j" req4m $end
$var reg 1 k" req5m $end
$var reg 1 l" req6m $end
$var reg 1 m" req7m $end
$var reg 1 n" req8m $end
$var reg 1 o" req9m $end
$upscope $end
$upscope $end
$enddefinitions $end
#0
$dumpvars
xo"
xn"
xm"
xl"
xk"
xj"
xi"
xh"
xg"
xf"
xe"
xd"
xc"
xb"
xa"
x`"
x_"
x^"
x]"
x\"
x["
xZ"
xY"
xX"
xW"
xV"
xU"
xT"
xS"
xR"
xQ"
xP"
zO"
zN"
zM"
xL"
xK"
xJ"
xI"
xH"
xG"
xF"
xE"
xD"
xC"
xB"
xA"
x@"
x?"
x>"
x="
x<"
x;"
x:"
x9"
x8"
x7"
x6"
x5"
z4"
z3"
z2"
x1"
x0"
x/"
x."
bx -"
bx ,"
bx +"
bx *"
bx )"
bx ("
bx '"
bx &"
bx %"
bx $"
bx #"
bx ""
bx !"
bx ~
bx }
bx |
bx {
bx z
bx y
bx x
bx w
bx v
bx u
bx t
bx s
bx r
bx q
bx p
bx o
bx n
bzxxxxxxxxxxxxxxxxxxxxxxxxxxxxxxxxxxxxxxxxxxxxxxxxxxxxxxxxxxxxxxxxx m
bx l
bzxxxxxxxxxxxxxxxxxxxxxxxxxxxxxxxxxxxxxxxxxxxxxxxxxxxxxxxxxxxxxxxxx k
bx j
bzxxxxxxxxxxxxxxxxxxxxxxxxxxxxxxxxxxxxxxxxxxxxxxxxxxxxxxxxxxxxxxxxx i
bx h
bzxxxxxxxxxxxxxxxxxxxxxxxxxxxxxxxxxxxxxxxxxxxxxxxxxxxxxxxxxxxxxxxxx g
bx f
bzxxxxxxxxxxxxxxxxxxxxxxxxxxxxxxxxxxxxxxxxxxxxxxxxxxxxxxxxxxxxxxxxx e
bx d
bzxxxxxxxxxxxxxxxxxxxxxxxxxxxxxxxxxxxxxxxxxxxxxxxxxxxxxxxxxxxxxxxxx c
bx b
bzxxxxxxxxxxxxxxxxxxxxxxxxxxxxxxxxxxxxxxxxxxxxxxxxxxxxxxxxxxxxxxxxx a
bx `
bzxxxxxxxxxxxxxxxxxxxxxxxxxxxxxxxxxxxxxxxxxxxxxxxxxxxxxxxxxxxxxxxxx _
bx ^
bzxxxxxxxxxxxxxxxxxxxxxxxxxxxxxxxxxxxxxxxxxxxxxxxxxxxxxxxxxxxxxxxxx ]
x\
x[
xZ
xY
xX
xW
xV
xU
xT
xS
xR
bx Q
bx P
bx O
bx N
bx M
bx L
bx K
bx J
b0xxxxxxxxxxxxxxxx I
b0xxxxxxxxxxxxxxx H
b0xxxxxxxxxxxxxx G
b0xxxxxxxxxxxxx F
b0xxxxxxxxxxxx E
b0xxxxxxxxxxx D
b0xxxxxxxxxx C
b0xxxxxxxxx B
bx A
bx @
bx ?
b0xxxxxxxxxxxxxxxx >
bx =
b0xxxxxxxxxxxxxxxx <
bx ;
bx :
bx 9
bx 8
bx 7
bx 6
bx 5
bx 4
b0xxxxxxxxxxxxxxxx 3
b0xxxxxxxxxxxxxxx 2
b0xxxxxxxxxxxxxx 1
b0xxxxxxxxxxxxx 0
b0xxxxxxxxxxxx /
b0xxxxxxxxxxx .
b0xxxxxxxxxx -
b0xxxxxxxxx ,
bx +
bx *
x)
z(
bz '
z&
bx %
bx $
z#
bz "
1!
$end
#5000
1K"
1J"
1L"
1H"
1G"
1I"
1E"
1D"
1F"
1B"
1A"
1C"
1?"
1>"
1@"
1<"
1;"
1="
19"
18"
1:"
16"
15"
17"
10"
1/"
11"
1)
1."
0S
0T
0U
0V
0W
0X
0Y
0Z
0[
0R
0S"
0T"
0R"
0e"
0o"
0d"
0c"
0n"
0b"
0a"
0m"
0`"
0_"
0l"
0^"
0]"
0k"
0\"
0["
0j"
0Z"
0Y"
0i"
0X"
0W"
0h"
0V"
0U"
0g"
0Q"
0P"
0f"
0&
b0 "
b0 '
0!
#10000
1!
#15000
0!
#20000
1!
#25000
0!
#30000
1!
#35000
0!
#40000
1!
#45000
0!
#50000
1!
#55000
0!
#60000
1!
#65000
0!
#70000
1!
#75000
0!
#80000
1!
#85000
0!
#90000
1!
#95000
0!
#100000
1!
#105000
1&
0!
#110000
x[
xQ"
xP"
xf"
1!
#115000
0!
#120000
xZ
xV"
xU"
xg"
1!
#125000
0!
#130000
xY
xX"
xW"
xh"
1!
#135000
0!
#140000
xX
xZ"
xY"
xi"
1!
#145000
0!
#150000
xW
x\"
x["
xj"
1!
#155000
0!
#160000
xV
x^"
x]"
xk"
1!
#165000
0!
#170000
xU
x`"
x_"
xl"
1!
#175000
0!
#180000
xT
xb"
xa"
xm"
1!
#185000
0!
#190000
xS
xd"
xc"
xn"
1!
#195000
0!
#200000
x)
x."
x0"
x/"
x1"
x6"
x5"
x7"
x9"
x8"
x:"
x<"
x;"
x="
x?"
x>"
x@"
xB"
xA"
xC"
xE"
xD"
xF"
xH"
xG"
xI"
xK"
xJ"
xL"
xR
xS"
xT"
xR"
xe"
xo"
1!
